codeforces_core/__init__.py
codeforces_core/account.py
codeforces_core/constants.py
codeforces_core/contest_list.py
codeforces_core/contest_meta.py
codeforces_core/contest_register.py
codeforces_core/contest_standing.py
codeforces_core/httphelper.py
codeforces_core/kwargs.py
codeforces_core/language.py
codeforces_core/logging.py
codeforces_core/problem.py
codeforces_core/problems.py
codeforces_core/py.typed
codeforces_core/settings.py
codeforces_core/submit.py
codeforces_core/url.py
codeforces_core/util.py
codeforces_core/websocket.py
codeforces_core/interfaces/AioHttpHelper.py
codeforces_core/interfaces/__init__.py
yxr_codeforces_core-0.0.2.5.dist-info/METADATA
yxr_codeforces_core-0.0.2.5.dist-info/WHEEL
yxr_codeforces_core-0.0.2.5.dist-info/licenses/LICENSE
yxr_codeforces_core-0.0.2.5.dist-info/RECORD
