Metadata-Version: 2.3
Name: yxr-codeforces-core
Version: 0.0.2.5
Summary: Simple Codeforces core api
Project-URL: Homepage, https://github.com/CroMarmot/yxr-codeforces-core
Project-URL: Bug Tracker, https://github.com/CroMarmot/yxr-codeforces-core/issues
Author-email: YeXiaoRain <yexiaorain@gmail.com>
License: MIT License
License-File: LICENSE
Keywords: api,codeforces,yxr
Classifier: License :: OSI Approved :: MIT License
Classifier: Programming Language :: Python :: 3
Requires-Python: >=3.8
Requires-Dist: aiohttp
Requires-Dist: beautifulsoup4
Requires-Dist: brotli
Requires-Dist: dataclasses-json
Requires-Dist: lxml
Requires-Dist: pyaes
Requires-Dist: requests
Provides-Extra: dev
Requires-Dist: build; extra == 'dev'
Requires-Dist: furo; extra == 'dev'
Requires-Dist: mypy; extra == 'dev'
Requires-Dist: myst-parser; extra == 'dev'
Requires-Dist: pytest-asyncio>=0.20; extra == 'dev'
Requires-Dist: pytest-cov; extra == 'dev'
Requires-Dist: pytest>=6; extra == 'dev'
Requires-Dist: sphinx~=5.3; extra == 'dev'
Requires-Dist: toml; extra == 'dev'
Requires-Dist: types-beautifulsoup4; extra == 'dev'
Requires-Dist: yapf; extra == 'dev'
Provides-Extra: doc
Requires-Dist: furo; extra == 'doc'
Requires-Dist: myst-parser; extra == 'doc'
Requires-Dist: sphinx~=5.3; extra == 'doc'
Provides-Extra: test
Requires-Dist: mypy; extra == 'test'
Requires-Dist: pytest-asyncio>=0.20; extra == 'test'
Requires-Dist: pytest-cov; extra == 'test'
Requires-Dist: pytest>=6; extra == 'test'
Requires-Dist: types-beautifulsoup4; extra == 'test'
